Metadata-Version: 2.4
Name: sharptools
Version: 0.5.0
Summary: Jednoduchý balíček s užitečnými funkcemi pro práci s čísly a textem.
Home-page: https://github.com/tvujprofil/ultimate
Author: UltimateTeam
Author-email: support@ultimateteam.com
Classifier: Programming Language :: Python :: 3
Classifier: License :: OSI Approved :: MIT License
Classifier: Operating System :: OS Independent
Requires-Python: >=3.6
License-File: LICENSE
Dynamic: author
Dynamic: author-email
Dynamic: classifier
Dynamic: description
Dynamic: description-content-type
Dynamic: home-page
Dynamic: license-file
Dynamic: requires-python
Dynamic: summary
